SiteMiner
