Metadata-Version: 1.1
Name: SiteMiner
Version: 0.1.6
Summary: crawl a site and find out all link http status code
Home-page: https://github.com/yangsibai/SiteMiner
Author: massimo
Author-email: yangsibai@gmail.com
License: MIT
Keywords: http status site error
Platform: UNKNOWN
Classifier: Development Status :: 3 - Alpha
Classifier: Topic :: Internet :: WWW/HTTP
Classifier: License :: OSI Approved :: MIT License
